dong_api/__init__.py
dong_api/auth.py
dong_api/model_user.py
dong_api/users.py
dong_api/depends/__init__.py
dong_api/depends/hash_user.py
dong_api/depends/validate.py
make_user_api-0.0.3.dist-info/METADATA
make_user_api-0.0.3.dist-info/WHEEL
make_user_api-0.0.3.dist-info/top_level.txt
make_user_api-0.0.3.dist-info/RECORD
